pybana/.DS_Store
pybana/__init__.py
pybana/client.py
pybana/constants.py
pybana/index.json
pybana/mappings.json
pybana/models.py
pybana/helpers/__init__.py
pybana/helpers/datasweet.py
pybana/helpers/math.py
pybana/helpers/vega.py
pybana/translators/__init__.py
pybana/translators/scope.py
pybana/translators/elastic/__init__.py
pybana/translators/elastic/buckets.py
pybana/translators/elastic/filter.py
pybana/translators/elastic/metrics.py
pybana/translators/vega/__init__.py
pybana/translators/vega/constants.py
pybana/translators/vega/metrics.py
pybana/translators/vega/vega.py
pybana/translators/vega/visualization.py
pybana-0.7.2.dist-info/AUTHORS.md
pybana-0.7.2.dist-info/LICENSE
pybana-0.7.2.dist-info/METADATA
pybana-0.7.2.dist-info/WHEEL
pybana-0.7.2.dist-info/top_level.txt
pybana-0.7.2.dist-info/RECORD
