Metadata-Version: 2.1
Name: pybana
Version: 0.7.2
Summary: Python client for kibana. Provide ORM & vega rendering of visualizations
Home-page: https://github.com/optimdata/pybana
Author: Guillaume Thomas
Author-email: guillaume.thomas@inuse.eu
License: MIT license
Keywords: pybana
Platform: UNKNOWN
Classifier: Development Status :: 2 - Pre-Alpha
Classifier: Intended Audience :: Developers
Classifier: License :: OSI Approved :: MIT License
Classifier: Natural Language :: English
Classifier: Programming Language :: Python :: 3
Classifier: Programming Language :: Python :: 3.6
Classifier: Programming Language :: Python :: 3.7
Requires-Dist: elasticsearch (==6.4.0)
Requires-Dist: elasticsearch-dsl (==6.4.0)
Requires-Dist: hjson (==3.0.1)
Requires-Dist: pytz (==2019.1)
